pvanalytics/__init__.py
pvanalytics/metrics.py
pvanalytics/system.py
pvanalytics/data/ac_power_inv_2173.csv
pvanalytics/data/ac_power_inv_2173_interpolated_data.csv
pvanalytics/data/ac_power_inv_2173_stale_data.csv
pvanalytics/data/ac_power_inv_7539.csv
pvanalytics/data/ac_power_inv_7539_outliers.csv
pvanalytics/data/irradiance_RMIS_NREL.csv
pvanalytics/data/midc_bms_ghi_20220120.csv
pvanalytics/data/nrel_1axis_tracker_mesa_ac_power.csv
pvanalytics/data/nrel_RSF_II.csv
pvanalytics/data/pvlib_data_shift.csv
pvanalytics/data/rmis_weather_data.csv
pvanalytics/data/serf_east_15min_ac_power.csv
pvanalytics/data/serf_east_1min_ac_power.csv
pvanalytics/data/serf_east_psm3_data.csv
pvanalytics/data/serf_west_15min.csv
pvanalytics/data/snow_data.csv
pvanalytics/data/snow_snowfall.csv
pvanalytics/data/system_15_poa_irradiance.parquet
pvanalytics/data/system_4_module_temperature.parquet
pvanalytics/data/system_50_ac_power_2_full_DST.parquet
pvanalytics/data/system_50_ac_power_2_full_DST_psm3.parquet
pvanalytics/features/__init__.py
pvanalytics/features/clearsky.py
pvanalytics/features/clipping.py
pvanalytics/features/daytime.py
pvanalytics/features/orientation.py
pvanalytics/features/shading.py
pvanalytics/features/snow.py
pvanalytics/quality/__init__.py
pvanalytics/quality/data_shifts.py
pvanalytics/quality/gaps.py
pvanalytics/quality/irradiance.py
pvanalytics/quality/outliers.py
pvanalytics/quality/time.py
pvanalytics/quality/util.py
pvanalytics/quality/weather.py
pvanalytics/tests/__init__.py
pvanalytics/tests/conftest.py
pvanalytics/tests/test_metrics.py
pvanalytics/tests/test_pvanalytics.py
pvanalytics/tests/test_system.py
pvanalytics/tests/features/__init__.py
pvanalytics/tests/features/test_clearsky.py
pvanalytics/tests/features/test_clipping.py
pvanalytics/tests/features/test_daytime.py
pvanalytics/tests/features/test_orientation.py
pvanalytics/tests/features/test_shading.py
pvanalytics/tests/features/test_snow.py
pvanalytics/tests/quality/__init__.py
pvanalytics-0.2.2.dist-info/LICENSE
pvanalytics-0.2.2.dist-info/METADATA
pvanalytics-0.2.2.dist-info/WHEEL
pvanalytics-0.2.2.dist-info/top_level.txt
pvanalytics-0.2.2.dist-info/RECORD
